unaflow/__init__.py
unaflow/_version.py
unaflow/dags/__init__.py
unaflow/dags/trigger/__init__.py
unaflow/dags/trigger_dag/__init__.py
unaflow/dags/trigger_dag/trigger_dag_configuration.py
unaflow/dags/trigger_dag/trigger_dag_factory.py
unaflow/dags/trigger_dag/providers/__init__.py
unaflow/dags/trigger_dag/providers/google/__init__.py
unaflow/dags/trigger_dag/providers/google/gcs_context_functions.py
unaflow/dags/trigger_dag/providers/google/gcs_trigger_dag_configuration.py
unaflow/functions/__init__.py
unaflow/functions/opsgenie.py
unaflow/functions/slack_functions.py
unaflow/operators/__init__.py
unaflow/operators/branch_dag_run_operator.py
unaflow/operators/check_dag_run_operator.py
unaflow/operators/clear_dag_operator.py
unaflow/operators/gcs_copy.py
unaflow/sensors/__init__.py
unaflow/sensors/external_dag_run_sensor.py
unaflow-0.6.10.dist-info/LICENSE
unaflow-0.6.10.dist-info/METADATA
unaflow-0.6.10.dist-info/WHEEL
unaflow-0.6.10.dist-info/top_level.txt
unaflow-0.6.10.dist-info/RECORD
